jpconvert/Pipeline.py
jpconvert/__init__.py
jpconvert/__main__.py
jpconvert/implementations/EmbedImages.py
jpconvert/implementations/FailIfOutputIsEmbedded.py
jpconvert/implementations/RemoveCellByMacro.py
jpconvert/implementations/RemoveEmptyCell.py
jpconvert/implementations/RemoveMacrosFromCode.py
jpconvert/implementations/RemoveMacrosFromTags.py
jpconvert/implementations/RemoveOutput.py
jpconvert/implementations/RemovePyCharm.py
jpconvert/implementations/RemoveRaisesExceptionTag.py
jpconvert/implementations/RemoveTrailingLines.py
jpconvert/implementations/SetReadonly.py
jpconvert/implementations/SetUndeletable.py
jpconvert/implementations/StripLines.py
jpconvert/implementations/TableOfContents.py
jpconvert/implementations/WrapSource.py
jpconvert/implementations/__init__.py
jpconvert/operations/CheckCell.py
jpconvert/operations/FilterCell.py
jpconvert/operations/FilterLine.py
jpconvert/operations/MapCell.py
jpconvert/operations/MapLine.py
jpconvert/operations/Operation.py
jpconvert/operations/__init__.py
jpconvert-0.3.19.dist-info/licenses/LICENSE
jpconvert-0.3.19.dist-info/METADATA
jpconvert-0.3.19.dist-info/WHEEL
jpconvert-0.3.19.dist-info/top_level.txt
jpconvert-0.3.19.dist-info/RECORD
