Metadata-Version: 2.4
Name: jpconvert
Version: 0.3.19
Summary: macros for Jupyter Notebooks
Home-page: https://github.com/erictroebs/jpconvert
Author: Eric Tröbs
Author-email: eric.troebs@tu-ilmenau.de
Project-URL: Bug Tracker, https://github.com/erictroebs/jpconvert/issues
Classifier: Programming Language :: Python :: 3
Classifier: License :: OSI Approved :: MIT License
Classifier: Operating System :: OS Independent
Requires-Python: >=3.10
License-File: LICENSE
Requires-Dist: nbformat~=5.10.4
Requires-Dist: requests~=2.32.4
Requires-Dist: python-magic~=0.4.27
Dynamic: author
Dynamic: author-email
Dynamic: classifier
Dynamic: description
Dynamic: description-content-type
Dynamic: home-page
Dynamic: license-file
Dynamic: project-url
Dynamic: requires-dist
Dynamic: requires-python
Dynamic: summary
